spriteworld/__init__.py
spriteworld/action_spaces.py
spriteworld/constants.py
spriteworld/demo_ui.py
spriteworld/environment.py
spriteworld/factor_distributions.py
spriteworld/gym_wrapper.py
spriteworld/shapes.py
spriteworld/sprite.py
spriteworld/sprite_generators.py
spriteworld/tasks.py
spriteworld/configs/__init__.py
spriteworld/configs/cobra/__init__.py
spriteworld/configs/cobra/clustering.py
spriteworld/configs/cobra/common.py
spriteworld/configs/cobra/exploration.py
spriteworld/configs/cobra/goal_finding_more_distractors.py
spriteworld/configs/cobra/goal_finding_more_targets.py
spriteworld/configs/cobra/goal_finding_new_position.py
spriteworld/configs/cobra/goal_finding_new_shape.py
spriteworld/configs/cobra/sorting.py
spriteworld/configs/examples/__init__.py
spriteworld/configs/examples/goal_finding_clustering.py
spriteworld/configs/examples/goal_finding_embodied.py
spriteworld/renderers/__init__.py
spriteworld/renderers/abstract_renderer.py
spriteworld/renderers/color_maps.py
spriteworld/renderers/handcrafted.py
spriteworld/renderers/pil_renderer.py
spriteworld-1.0.2.dist-info/LICENSE
spriteworld-1.0.2.dist-info/METADATA
spriteworld-1.0.2.dist-info/WHEEL
spriteworld-1.0.2.dist-info/top_level.txt
spriteworld-1.0.2.dist-info/RECORD
