Metadata-Version: 2.1
Name: spriteworld
Version: 1.0.2
Summary: Spriteworld is a python-based reinforcement learning environment consisting of a 2-dimensional arena with objects that can be freely moved.
Home-page: https://github.com/deepmind/spriteworld/
Author: DeepMind
License: Apache License, Version 2.0
Keywords: ai,reinforcement-learning,python,machine learning,objects
Platform: UNKNOWN
Classifier: Development Status :: 5 - Production/Stable
Classifier: Environment :: Console
Classifier: Intended Audience :: Science/Research
Classifier: License :: OSI Approved :: Apache Software License
Classifier: Operating System :: POSIX :: Linux
Classifier: Operating System :: Microsoft :: Windows
Classifier: Operating System :: MacOS :: MacOS X
Classifier: Programming Language :: Python :: 2.7
Classifier: Programming Language :: Python :: 3.4
Classifier: Programming Language :: Python :: 3.5
Classifier: Programming Language :: Python :: 3.6
Classifier: Programming Language :: Python :: 3.7
Classifier: Topic :: Scientific/Engineering :: Artificial Intelligence
Requires-Dist: absl-py
Requires-Dist: dm-env
Requires-Dist: enum34
Requires-Dist: matplotlib
Requires-Dist: mock
Requires-Dist: numpy
Requires-Dist: pillow
Requires-Dist: scikit-learn
Requires-Dist: six
Provides-Extra: gym
Requires-Dist: gym ; extra == 'gym'
